pyaiui/__init__.py
pyaiui/_pyaiui.py
pyaiui-5.6.1071.0.data/data/pyaiui/libs/ELF/32bit/libaiui.so
pyaiui-5.6.1071.0.data/data/pyaiui/libs/ELF/64bit/libaiui.so
pyaiui-5.6.1071.0.data/data/pyaiui/libs/WindowsPE/32bit/libaiui.so
pyaiui-5.6.1071.0.data/data/pyaiui/libs/WindowsPE/64bit/libaiui.so
pyaiui-5.6.1071.0.dist-info/METADATA
pyaiui-5.6.1071.0.dist-info/WHEEL
pyaiui-5.6.1071.0.dist-info/top_level.txt
pyaiui-5.6.1071.0.dist-info/RECORD
