Metadata-Version: 2.1
Name: pyaiui
Version: 5.6.1071.0
Summary: aiui sdk for python.
Home-page: https://aiui.xfyun.cn
Author: zrmei
Author-email: zrmei@iflytek.com
License: UNKNOWN
Platform: UNKNOWN
Classifier: Programming Language :: Python :: 3
Classifier: License :: OSI Approved :: MIT License
Classifier: Operating System :: OS Independent
Requires-Python: >=3.5
